doudian/__init__.py
doudian/core.py
doudian/exception.py
doudian/type.py
doudian-0.6.dist-info/LICENSE
doudian-0.6.dist-info/METADATA
doudian-0.6.dist-info/WHEEL
doudian-0.6.dist-info/top_level.txt
doudian-0.6.dist-info/RECORD
