Metadata-Version: 2.1
Name: doudian
Version: 0.6
Summary: 抖店 Python SDK(doudian python sdk)
Home-page: https://github.com/minibear2021/doudian
Author: minibear
License: MIT
Keywords: python sdk doudian jinritemai 抖店
Platform: UNKNOWN
Classifier: Development Status :: 4 - Beta
Classifier: Topic :: Office/Business
Classifier: License :: OSI Approved :: MIT License
Classifier: Programming Language :: Python :: 3
License-File: LICENSE
Requires-Dist: requests (>=2.21.0)
Requires-Dist: cryptography (>=2.2.2)
